odoo/addons/product_restricted_type/README.rst
odoo/addons/product_restricted_type/__init__.py
odoo/addons/product_restricted_type/__manifest__.py
odoo/addons/product_restricted_type/i18n/ca.po
odoo/addons/product_restricted_type/i18n/es.po
odoo/addons/product_restricted_type/i18n/product_restricted_type.pot
odoo/addons/product_restricted_type/models/__init__.py
odoo/addons/product_restricted_type/models/product.py
odoo/addons/product_restricted_type/models/product_template.py
odoo/addons/product_restricted_type/readme/CONTRIBUTORS.rst
odoo/addons/product_restricted_type/readme/DESCRIPTION.rst
odoo/addons/product_restricted_type/readme/USAGE.rst
odoo/addons/product_restricted_type/static/description/icon.png
odoo/addons/product_restricted_type/static/description/index.html
odoo/addons/product_restricted_type/tests/__init__.py
odoo/addons/product_restricted_type/tests/test_product_restricted_type.py
odoo/addons/product_restricted_type/views/product_views.xml
odoo14_addon_product_restricted_type-14.0.1.0.1.dist-info/METADATA
odoo14_addon_product_restricted_type-14.0.1.0.1.dist-info/WHEEL
odoo14_addon_product_restricted_type-14.0.1.0.1.dist-info/top_level.txt
odoo14_addon_product_restricted_type-14.0.1.0.1.dist-info/RECORD
